tnc/__init__.py
tnc/cli.py
tnc/core.py
tnc/keys.py
tnc/logger.py
tnc/protector.py
trustnocorpo-1.0.0.dist-info/licenses/LICENSE
trustnocorpo-1.0.0.dist-info/METADATA
trustnocorpo-1.0.0.dist-info/WHEEL
trustnocorpo-1.0.0.dist-info/entry_points.txt
trustnocorpo-1.0.0.dist-info/top_level.txt
trustnocorpo-1.0.0.dist-info/RECORD
