Metadata-Version: 2.4
Name: trustnocorpo
Version: 1.0.0
Summary: Cryptographic PDF tracking for LaTeX with optional PDF protection and encrypted audit logs.
Author: TrustNoCorpo Security Team
License: MIT
Project-URL: Homepage, https://example.com/trustnocorpo
Keywords: latex,pdf,security,cryptography,watermark,cli
Classifier: Development Status :: 4 - Beta
Classifier: Intended Audience :: Developers
Classifier: Intended Audience :: Information Technology
Classifier: License :: OSI Approved :: MIT License
Classifier: Programming Language :: Python
Classifier: Programming Language :: Python :: 3
Classifier: Programming Language :: Python :: 3 :: Only
Classifier: Programming Language :: Python :: 3.9
Classifier: Programming Language :: Python :: 3.10
Classifier: Programming Language :: Python :: 3.11
Classifier: Programming Language :: Python :: 3.12
Classifier: Operating System :: OS Independent
Classifier: Topic :: Security :: Cryptography
Classifier: Topic :: Text Processing :: Markup :: LaTeX
Classifier: Environment :: Console
Requires-Python: >=3.9
License-File: LICENSE
Requires-Dist: cryptography>=42.0.0
Requires-Dist: pypdf>=4.2.0
Dynamic: license-file
